YouTubeDownloader/__init__.py
YouTubeDownloader-1.1.3.dist-info/LICENSE
YouTubeDownloader-1.1.3.dist-info/METADATA
YouTubeDownloader-1.1.3.dist-info/WHEEL
YouTubeDownloader-1.1.3.dist-info/entry_points.txt
YouTubeDownloader-1.1.3.dist-info/top_level.txt
YouTubeDownloader-1.1.3.dist-info/RECORD
