Metadata-Version: 2.1
Name: YouTubeDownloader
Version: 1.1.3
Summary: A simple to use youtube playlists/videos/audios downloader
Home-page: https://github.com/Jodagito/YoutubeDownloader
Author: Jodagito
License: UNKNOWN
Platform: UNKNOWN
Classifier: Programming Language :: Python :: 3.6
Classifier: License :: OSI Approved :: MIT License
Classifier: Operating System :: OS Independent
Requires-Python: >=3.6
Requires-Dist: pytube3 (>=9.5.13)
